ss_riscv/src/rv32i_defs.vh
`ifndef RV32I_DEFS_VH
`define RV32I_DEFS_VH

// Opcodes
`define OPC_LUI       7'b0110111
`define OPC_AUIPC     7'b0010111
`define OPC_JAL       7'b1101111
`define OPC_JALR      7'b1100111
`define OPC_BRANCH    7'b1100011
`define OPC_LOAD      7'b0000011
`define OPC_STORE     7'b0100011
`define OPC_OPIMM     7'b0010011
`define OPC_OP        7'b0110011
`define OPC_MISC_MEM  7'b0001111
`define OPC_SYSTEM    7'b1110011

// funct3 for ALU ops
`define F3_ADD_SUB  3'b000
`define F3_SLL      3'b001
`define F3_SLT      3'b010
`define F3_SLTU     3'b011
`define F3_XOR      3'b100
`define F3_SRL_SRA  3'b101
`define F3_OR       3'b110
`define F3_AND      3'b111

// Branch funct3
`define F3_BEQ  3'b000
`define F3_BNE  3'b001
`define F3_BLT  3'b100
`define F3_BGE  3'b101
`define F3_BLTU 3'b110
`define F3_BGEU 3'b111

// Load funct3
`define F3_LB   3'b000
`define F3_LH   3'b001
`define F3_LW   3'b010
`define F3_LBU  3'b100
`define F3_LHU  3'b101

// Store funct3
`define F3_SB   3'b000
`define F3_SH   3'b001
`define F3_SW   3'b010

// ALU operation encoding
`define ALU_ADD  4'b0000
`define ALU_SUB  4'b0001
`define ALU_SLL  4'b0010
`define ALU_SLT  4'b0011
`define ALU_SLTU 4'b0100
`define ALU_XOR  4'b0101
`define ALU_SRL  4'b0110
`define ALU_SRA  4'b0111
`define ALU_OR   4'b1000
`define ALU_AND  4'b1001

// Immediate select encoding
`define IMM_I 3'b000
`define IMM_S 3'b001
`define IMM_B 3'b010
`define IMM_U 3'b011
`define IMM_J 3'b100

`endif // RV32I_DEFS_VH

ss_riscv/src/data_mem.v
`include "rv32i_defs.vh"

// Simulation-only data RAM
module sim_data_ram #(
    parameter MEM_WORDS = 1024
) (
    input              clk,
    input              mem_read,
    input              mem_write,
    input      [2:0]   funct3,
    input      [31:0]  addr,
    input      [31:0]  wdata,
    output reg [31:0]  rdata
);
    reg [31:0] mem [0:MEM_WORDS-1];

    integer i;
    initial begin
        for (i = 0; i < MEM_WORDS; i = i + 1) mem[i] = 32'b0;
    end

    wire [31:0] widx = addr[31:2];
    wire [1:0]  byte_off = addr[1:0];

    // Combinational read
    always @* begin
        if (mem_read && widx < MEM_WORDS) begin
            case (funct3)
                `F3_LB: begin
                    case (byte_off)
                        2'd0: rdata = {{24{mem[widx][7]}},  mem[widx][7:0]};
                        2'd1: rdata = {{24{mem[widx][15]}}, mem[widx][15:8]};
                        2'd2: rdata = {{24{mem[widx][23]}}, mem[widx][23:16]};
                        2'd3: rdata = {{24{mem[widx][31]}}, mem[widx][31:24]};
                    endcase
                end
                `F3_LBU: begin
                    case (byte_off)
                        2'd0: rdata = {24'b0, mem[widx][7:0]};
                        2'd1: rdata = {24'b0, mem[widx][15:8]};
                        2'd2: rdata = {24'b0, mem[widx][23:16]};
                        2'd3: rdata = {24'b0, mem[widx][31:24]};
                    endcase
                end
                `F3_LH: begin
                    case (byte_off[1]) // aligned 0 or 2
                        1'b0: rdata = {{16{mem[widx][15]}}, mem[widx][15:0]};
                        1'b1: rdata = {{16{mem[widx][31]}}, mem[widx][31:16]};
                    endcase
                end
                `F3_LHU: begin
                    case (byte_off[1])
                        1'b0: rdata = {16'b0, mem[widx][15:0]};
                        1'b1: rdata = {16'b0, mem[widx][31:16]};
                    endcase
                end
                `F3_LW: begin
                    if (byte_off == 2'b00) rdata = mem[widx];
                    else rdata = 32'b0; // misaligned -> 0
                end
                default: rdata = 32'b0;
            endcase
        end else begin
            rdata = 32'b0;
        end
    end

    // Synchronous write
    always @(posedge clk) begin
        if (mem_write && widx < MEM_WORDS) begin
            case (funct3)
                `F3_SB: begin
                    case (byte_off)
                        2'd0: mem[widx][7:0]   <= wdata[7:0];
                        2'd1: mem[widx][15:8]  <= wdata[7:0];
                        2'd2: mem[widx][23:16] <= wdata[7:0];
                        2'd3: mem[widx][31:24] <= wdata[7:0];
                    endcase
                end
                `F3_SH: begin
                    case (byte_off[1])
                        1'b0: mem[widx][15:0]  <= wdata[15:0];
                        1'b1: mem[widx][31:16] <= wdata[15:0];
                    endcase
                end
                `F3_SW: begin
                    if (byte_off == 2'b00) mem[widx] <= wdata;
                end
                default: ;
            endcase
        end
    end
endmodule

ss_riscv/src/instr_mem.v
// Simulation-only instruction ROM with hex initialization
module sim_instr_rom #(
    parameter MEM_WORDS = 1024,
    parameter INIT_HEX  = "programs/add_store.hex"
) (
    input  [31:0] addr,
    output [31:0] rdata
);
    reg [31:0] mem [0:MEM_WORDS-1];

    initial begin
        integer i;
        for (i = 0; i < MEM_WORDS; i = i + 1) mem[i] = 32'h00000013; // NOPs
        $readmemh(INIT_HEX, mem);
    end

    wire [31:0] idx = addr[31:2];
    assign rdata = (idx < MEM_WORDS) ? mem[idx] : 32'h00000013; // NOP if OOB
endmodule

ss_riscv/src/branch_comp.v
`include "rv32i_defs.vh"

module branch_comp(
    input  [31:0] a,
    input  [31:0] b,
    input  [2:0]  funct3,
    output reg    take
);
    wire signed [31:0] as = a;
    wire signed [31:0] bs = b;
    always @* begin
        case (funct3)
            `F3_BEQ:  take = (a == b);
            `F3_BNE:  take = (a != b);
            `F3_BLT:  take = (as < bs);
            `F3_BGE:  take = (as >= bs);
            `F3_BLTU: take = (a < b);
            `F3_BGEU: take = (a >= b);
            default:  take = 1'b0;
        endcase
    end
endmodule

ss_riscv/src/alu.v
`include "rv32i_defs.vh"

module rv32i_alu(
    input  [31:0] a,
    input  [31:0] b,
    input  [3:0]  alu_op,
    output reg [31:0] y
);
    wire signed [31:0] as = a;
    wire signed [31:0] bs = b;
    always @* begin
        case (alu_op)
            `ALU_ADD:  y = a + b;
            `ALU_SUB:  y = a - b;
            `ALU_SLL:  y = a << b[4:0];
            `ALU_SLT:  y = (as < bs) ? 32'd1 : 32'd0;
            `ALU_SLTU: y = (a < b)  ? 32'd1 : 32'd0;
            `ALU_XOR:  y = a ^ b;
            `ALU_SRL:  y = a >> b[4:0];
            `ALU_SRA:  y = as >>> b[4:0];
            `ALU_OR:   y = a | b;
            `ALU_AND:  y = a & b;
            default:   y = 32'b0;
        endcase
    end
endmodule

ss_riscv/src/imm_gen.v
`include "rv32i_defs.vh"

module imm_gen(
    input  [31:0] instr,
    input  [2:0]  imm_sel,
    output reg [31:0] imm
);
    wire [31:0] imm_i = {{20{instr[31]}}, instr[31:20]};
    wire [31:0] imm_s = {{20{instr[31]}}, instr[31:25], instr[11:7]};
    wire [31:0] imm_b = {{19{instr[31]}}, instr[31], instr[7], instr[30:25], instr[11:8], 1'b0};
    wire [31:0] imm_u = {instr[31:12], 12'b0};
    wire [31:0] imm_j = {{11{instr[31]}}, instr[31], instr[19:12], instr[20], instr[30:21], 1'b0};

    always @* begin
        case (imm_sel)
            `IMM_I: imm = imm_i;
            `IMM_S: imm = imm_s;
            `IMM_B: imm = imm_b;
            `IMM_U: imm = imm_u;
            `IMM_J: imm = imm_j;
            default: imm = 32'b0;
        endcase
    end
endmodule

ss_riscv/src/regfile.v
module regfile(
    input              clk,
    input              reset,
    input              we,
    input      [4:0]   rs1,
    input      [4:0]   rs2,
    input      [4:0]   rd,
    input      [31:0]  wd,
    output     [31:0]  rd1,
    output     [31:0]  rd2
);
    reg [31:0] regs [0:31];

    // x0 always zero
    assign rd1 = (rs1 == 5'd0) ? 32'b0 : regs[rs1];
    assign rd2 = (rs2 == 5'd0) ? 32'b0 : regs[rs2];

    integer i;
    always @(posedge clk) begin
        if (reset) begin
            for (i = 0; i < 32; i = i + 1) regs[i] <= 32'b0;
        end else if (we && rd != 5'd0) begin
            regs[rd] <= wd;
        end
    end
endmodule

ss_riscv/src/control_unit.v
`include "rv32i_defs.vh"

module control_unit(
    input  [31:0] instr,
    output reg [2:0]  imm_sel,
    output reg [3:0]  alu_op,
    output reg        a_sel_pc,
    output reg        a_sel_zero,
    output reg        b_sel_imm,
    output reg        branch,
    output reg        jal,
    output reg        jalr,
    output reg        mem_read,
    output reg        mem_write,
    output reg [1:0]  wb_sel,   // 00 ALU, 01 MEM, 10 PC+4
    output reg        reg_write
);
    wire [6:0] opcode = instr[6:0];
    wire [2:0] funct3 = instr[14:12];
    wire [6:0] funct7 = instr[31:25];

    always @* begin
        // defaults (NOP)
        imm_sel   = `IMM_I;
        alu_op    = `ALU_ADD;
        a_sel_pc  = 1'b0;
        a_sel_zero= 1'b0;
        b_sel_imm = 1'b0;
        branch    = 1'b0;
        jal       = 1'b0;
        jalr      = 1'b0;
        mem_read  = 1'b0;
        mem_write = 1'b0;
        wb_sel    = 2'b00;
        reg_write = 1'b0;

        case (opcode)
            `OPC_LUI: begin
                imm_sel   = `IMM_U;
                a_sel_zero= 1'b1; // 0 + imm
                b_sel_imm = 1'b1;
                alu_op    = `ALU_ADD;
                wb_sel    = 2'b00; // ALU result = imm
                reg_write = 1'b1;
            end
            `OPC_AUIPC: begin
                imm_sel   = `IMM_U;
                a_sel_pc  = 1'b1; // PC + imm
                b_sel_imm = 1'b1;
                alu_op    = `ALU_ADD;
                wb_sel    = 2'b00;
                reg_write = 1'b1;
            end
            `OPC_JAL: begin
                imm_sel   = `IMM_J;
                jal       = 1'b1;
                wb_sel    = 2'b10; // PC+4
                reg_write = 1'b1;
            end
            `OPC_JALR: begin
                imm_sel   = `IMM_I;
                jalr      = 1'b1;
                wb_sel    = 2'b10; // PC+4
                reg_write = 1'b1;
            end
            `OPC_BRANCH: begin
                imm_sel   = `IMM_B;
                branch    = 1'b1;
                // ALU not used for PC calculation; comparator uses rs1/rs2
            end
            `OPC_LOAD: begin
                imm_sel   = `IMM_I;
                a_sel_pc  = 1'b0;
                b_sel_imm = 1'b1; // rs1 + imm
                alu_op    = `ALU_ADD;
                mem_read  = 1'b1;
                wb_sel    = 2'b01; // MEM
                reg_write = 1'b1;
            end
            `OPC_STORE: begin
                imm_sel   = `IMM_S;
                b_sel_imm = 1'b1;
                alu_op    = `ALU_ADD; // addr = rs1 + imm
                mem_write = 1'b1;
            end
            `OPC_OPIMM: begin
                imm_sel   = `IMM_I;
                b_sel_imm = 1'b1;
                reg_write = 1'b1;
                wb_sel    = 2'b00;
                // ALU op by funct3/funct7
                case (funct3)
                    `F3_ADD_SUB: alu_op = `ALU_ADD; // ADDI
                    `F3_SLL:     alu_op = `ALU_SLL; // SLLI
                    `F3_SLT:     alu_op = `ALU_SLT; // SLTI
                    `F3_SLTU:    alu_op = `ALU_SLTU; // SLTIU
                    `F3_XOR:     alu_op = `ALU_XOR; // XORI
                    `F3_SRL_SRA: alu_op = (funct7[5]) ? `ALU_SRA : `ALU_SRL; // SRAI/SRLI
                    `F3_OR:      alu_op = `ALU_OR;  // ORI
                    `F3_AND:     alu_op = `ALU_AND; // ANDI
                    default:     alu_op = `ALU_ADD;
                endcase
            end
            `OPC_OP: begin
                reg_write = 1'b1;
                wb_sel    = 2'b00;
                // Determine ALU op from funct3 and bit30
                case (funct3)
                    `F3_ADD_SUB: alu_op = (funct7[5]) ? `ALU_SUB : `ALU_ADD;
                    `F3_SLL:     alu_op = `ALU_SLL;
                    `F3_SLT:     alu_op = `ALU_SLT;
                    `F3_SLTU:    alu_op = `ALU_SLTU;
                    `F3_XOR:     alu_op = `ALU_XOR;
                    `F3_SRL_SRA: alu_op = (funct7[5]) ? `ALU_SRA : `ALU_SRL;
                    `F3_OR:      alu_op = `ALU_OR;
                    `F3_AND:     alu_op = `ALU_AND;
                    default:     alu_op = `ALU_ADD;
                endcase
            end
            default: begin
                // NOP / SYSTEM not implemented
            end
        endcase
    end
endmodule

ss_riscv/src/rv32i_single_cycle.v
`include "rv32i_defs.vh"

// Synthesizable single-cycle RV32I core with external instruction and data memory interfaces.
module rv32i_single_cycle(
    input         clk,
    input         reset,

    // Instruction fetch interface (combinational read)
    output [31:0] imem_addr,
    input  [31:0] imem_rdata,

    // Data memory interface (combinational read, sync write)
    output        dmem_read,
    output        dmem_write,
    output [2:0]  dmem_funct3,
    output [31:0] dmem_addr,
    output [31:0] dmem_wdata,
    input  [31:0] dmem_rdata
);
    // Program counter
    reg [31:0] pc;
    wire [31:0] pc4 = pc + 32'd4;

    // Fetch
    assign imem_addr = pc;
    wire [31:0] instr = imem_rdata;

    // Decode fields
    wire [4:0] rd     = instr[11:7];
    wire [2:0] funct3 = instr[14:12];
    wire [4:0] rs1    = instr[19:15];
    wire [4:0] rs2    = instr[24:20];

    // Control
    wire [2:0] imm_sel;
    wire [3:0] alu_op;
    wire       a_sel_pc, a_sel_zero, b_sel_imm;
    wire       branch, jal, jalr;
    wire       mem_read, mem_write;
    wire [1:0] wb_sel;
    wire       reg_write;

    control_unit ctrl(
        .instr(instr),
        .imm_sel(imm_sel),
        .alu_op(alu_op),
        .a_sel_pc(a_sel_pc),
        .a_sel_zero(a_sel_zero),
        .b_sel_imm(b_sel_imm),
        .branch(branch),
        .jal(jal),
        .jalr(jalr),
        .mem_read(mem_read),
        .mem_write(mem_write),
        .wb_sel(wb_sel),
        .reg_write(reg_write)
    );

    // Register file
    wire [31:0] rs1_val, rs2_val;
    wire [31:0] wb_data;
    regfile rf(
        .clk(clk),
        .reset(reset),
        .we(reg_write),
        .rs1(rs1), .rs2(rs2), .rd(rd),
        .wd(wb_data),
        .rd1(rs1_val), .rd2(rs2_val)
    );

    // Immediates
    wire [31:0] imm;
    imm_gen ig(
        .instr(instr),
        .imm_sel(imm_sel),
        .imm(imm)
    );

    // ALU
    wire [31:0] alu_a = a_sel_zero ? 32'b0 : (a_sel_pc ? pc : rs1_val);
    wire [31:0] alu_b = b_sel_imm ? imm : rs2_val;
    wire [31:0] alu_y;
    rv32i_alu alu(
        .a(alu_a), .b(alu_b), .alu_op(alu_op), .y(alu_y)
    );

    // Data memory wires
    assign dmem_read  = mem_read;
    assign dmem_write = mem_write;
    assign dmem_funct3= funct3;
    assign dmem_addr  = alu_y;
    assign dmem_wdata = rs2_val;
    wire [31:0] load_data = dmem_rdata;

    // Branch compare
    wire br_take;
    branch_comp bc(
        .a(rs1_val), .b(rs2_val), .funct3(funct3), .take(br_take)
    );

    // Next PC logic
    wire [31:0] jalr_target = (rs1_val + imm) & ~32'd1;
    wire [31:0] br_target   = pc + imm;
    wire [31:0] jal_target  = pc + imm;

    wire take_branch = branch & br_take;

    wire [31:0] pc_next = jal  ? jal_target  :
                          jalr ? jalr_target :
                          take_branch ? br_target :
                          pc4;

    // Writeback mux
    assign wb_data = (wb_sel == 2'b00) ? alu_y :
                     (wb_sel == 2'b01) ? load_data :
                     (wb_sel == 2'b10) ? pc4 : 32'b0;

    // PC register
    always @(posedge clk or posedge reset) begin
        if (reset) pc <= 32'b0;
        else       pc <= pc_next;
    end
endmodule

ss_riscv/src/sim_top.v
`timescale 1ns/1ps

module sim_top;
    reg clk = 0;
    reg reset = 1;

    always #5 clk = ~clk;

    wire [31:0] imem_addr;
    wire [31:0] imem_rdata;

    wire        dmem_read;
    wire        dmem_write;
    wire [2:0]  dmem_funct3;
    wire [31:0] dmem_addr;
    wire [31:0] dmem_wdata;
    wire [31:0] dmem_rdata;

    rv32i_single_cycle core(
        .clk(clk), .reset(reset),
        .imem_addr(imem_addr), .imem_rdata(imem_rdata),
        .dmem_read(dmem_read), .dmem_write(dmem_write), .dmem_funct3(dmem_funct3),
        .dmem_addr(dmem_addr), .dmem_wdata(dmem_wdata), .dmem_rdata(dmem_rdata)
    );

    sim_instr_rom #(.MEM_WORDS(64), .INIT_HEX("programs/add_store.hex")) rom(
        .addr(imem_addr),
        .rdata(imem_rdata)
    );

    sim_data_ram #(.MEM_WORDS(64)) ram(
        .clk(clk),
        .mem_read(dmem_read), .mem_write(dmem_write), .funct3(dmem_funct3),
        .addr(dmem_addr), .wdata(dmem_wdata), .rdata(dmem_rdata)
    );

endmodule

ss_riscv/src/tb/tb_single_cycle.v
`timescale 1ns/1ps

module tb_single_cycle;
    reg clk = 0;
    reg reset = 1;

    // Clock generation: 10ns period
    always #5 clk = ~clk;

    sim_top dut();

    initial begin
        $dumpfile("wave.vcd");
        $dumpvars(0, tb_single_cycle);

        // Drive reset inside sim_top via force/release
        force dut.reset = 1'b1;
        repeat (3) @(posedge clk);
        force dut.reset = 1'b0;
        release dut.reset;

        // Run for some cycles
        repeat (50) @(posedge clk);

        // Peek data memory word 0
        $display("DMEM[0] = %0d (0x%08x)", dut.ram.mem[0], dut.ram.mem[0]);

        $finish;
    end
endmodule

ss_riscv/src/wave.vcd
$date
	Fri Oct 10 13:27:20 2025
$end
$version
	Icarus Verilog
$end
$timescale
	1ps
$end
$scope module tb_single_cycle $end
$var reg 1 ! clk $end
$var reg 1 " reset $end
$scope module dut $end
$var wire 32 # imem_rdata [31:0] $end
$var wire 32 $ imem_addr [31:0] $end
$var wire 1 % dmem_write $end
$var wire 32 & dmem_wdata [31:0] $end
$var wire 1 ' dmem_read $end
$var wire 32 ( dmem_rdata [31:0] $end
$var wire 3 ) dmem_funct3 [2:0] $end
$var wire 32 * dmem_addr [31:0] $end
$var reg 1 + clk $end
$var reg 1 , reset $end
$scope module core $end
$var wire 1 + clk $end
$var wire 32 - dmem_addr [31:0] $end
$var wire 3 . dmem_funct3 [2:0] $end
$var wire 1 ' dmem_read $end
$var wire 32 / dmem_wdata [31:0] $end
$var wire 1 % dmem_write $end
$var wire 32 0 imem_addr [31:0] $end
$var wire 32 1 instr [31:0] $end
$var wire 32 2 jalr_target [31:0] $end
$var wire 32 3 load_data [31:0] $end
$var wire 1 , reset $end
$var wire 1 4 take_branch $end
$var wire 2 5 wb_sel [1:0] $end
$var wire 32 6 wb_data [31:0] $end
$var wire 32 7 rs2_val [31:0] $end
$var wire 5 8 rs2 [4:0] $end
$var wire 32 9 rs1_val [31:0] $end
$var wire 5 : rs1 [4:0] $end
$var wire 1 ; reg_write $end
$var wire 5 < rd [4:0] $end
$var wire 32 = pc_next [31:0] $end
$var wire 32 > pc4 [31:0] $end
$var wire 1 ? mem_write $end
$var wire 1 @ mem_read $end
$var wire 1 A jalr $end
$var wire 32 B jal_target [31:0] $end
$var wire 1 C jal $end
$var wire 3 D imm_sel [2:0] $end
$var wire 32 E imm [31:0] $end
$var wire 32 F imem_rdata [31:0] $end
$var wire 3 G funct3 [2:0] $end
$var wire 32 H dmem_rdata [31:0] $end
$var wire 1 I branch $end
$var wire 32 J br_target [31:0] $end
$var wire 1 K br_take $end
$var wire 1 L b_sel_imm $end
$var wire 32 M alu_y [31:0] $end
$var wire 4 N alu_op [3:0] $end
$var wire 32 O alu_b [31:0] $end
$var wire 32 P alu_a [31:0] $end
$var wire 1 Q a_sel_zero $end
$var wire 1 R a_sel_pc $end
$var reg 32 S pc [31:0] $end
$scope module alu $end
$var wire 32 T a [31:0] $end
$var wire 32 U as [31:0] $end
$var wire 32 V b [31:0] $end
$var wire 32 W bs [31:0] $end
$var wire 4 X alu_op [3:0] $end
$var reg 32 Y y [31:0] $end
$upscope $end
$scope module bc $end
$var wire 32 Z as [31:0] $end
$var wire 32 [ bs [31:0] $end
$var wire 3 \ funct3 [2:0] $end
$var wire 32 ] b [31:0] $end
$var wire 32 ^ a [31:0] $end
$var reg 1 K take $end
$upscope $end
$scope module ctrl $end
$var wire 32 _ instr [31:0] $end
$var wire 7 ` opcode [6:0] $end
$var wire 7 a funct7 [6:0] $end
$var wire 3 b funct3 [2:0] $end
$var reg 1 R a_sel_pc $end
$var reg 1 Q a_sel_zero $end
$var reg 4 c alu_op [3:0] $end
$var reg 1 L b_sel_imm $end
$var reg 1 I branch $end
$var reg 3 d imm_sel [2:0] $end
$var reg 1 C jal $end
$var reg 1 A jalr $end
$var reg 1 @ mem_read $end
$var reg 1 ? mem_write $end
$var reg 1 ; reg_write $end
$var reg 2 e wb_sel [1:0] $end
$upscope $end
$scope module ig $end
$var wire 3 f imm_sel [2:0] $end
$var wire 32 g instr [31:0] $end
$var wire 32 h imm_u [31:0] $end
$var wire 32 i imm_s [31:0] $end
$var wire 32 j imm_j [31:0] $end
$var wire 32 k imm_i [31:0] $end
$var wire 32 l imm_b [31:0] $end
$var reg 32 m imm [31:0] $end
$upscope $end
$scope module rf $end
$var wire 1 + clk $end
$var wire 5 n rd [4:0] $end
$var wire 1 , reset $end
$var wire 5 o rs1 [4:0] $end
$var wire 5 p rs2 [4:0] $end
$var wire 32 q wd [31:0] $end
$var wire 1 ; we $end
$var wire 32 r rd2 [31:0] $end
$var wire 32 s rd1 [31:0] $end
$var integer 32 t i [31:0] $end
$upscope $end
$upscope $end
$scope module ram $end
$var wire 32 u addr [31:0] $end
$var wire 1 + clk $end
$var wire 3 v funct3 [2:0] $end
$var wire 1 ' mem_read $end
$var wire 1 % mem_write $end
$var wire 32 w wdata [31:0] $end
$var wire 32 x widx [31:0] $end
$var wire 2 y byte_off [1:0] $end
$var parameter 32 z MEM_WORDS $end
$var reg 32 { rdata [31:0] $end
$var integer 32 | i [31:0] $end
$upscope $end
$scope module rom $end
$var wire 32 } addr [31:0] $end
$var wire 32 ~ rdata [31:0] $end
$var wire 32 !" idx [31:0] $end
$var parameter 176 "" INIT_HEX $end
$var parameter 32 #" MEM_WORDS $end
$scope begin $unm_blk_19 $end
$var integer 32 $" i [31:0] $end
$upscope $end
$upscope $end
$upscope $end
$upscope $end
$enddefinitions $end
$comment Show the parameter values. $end
$dumpall
b1000000 #"
b1110000011100100110111101100111011100100110000101101101011100110010111101100001011001000110010001011111011100110111010001101111011100100110010100101110011010000110010101111000 ""
b1000000 z
$end
#0
$dumpvars
b1000000 $"
b0xxxxxxxxxxxxxxxxxxxxxxxxxxxxxx !"
bx ~
bx }
b1000000 |
b0 {
bx y
b0xxxxxxxxxxxxxxxxxxxxxxxxxxxxxx x
bx w
bx v
bx u
bx t
bx s
bx r
bx q
bx p
bx o
bx n
b0 m
bx0 l
bx k
bx0 j
bx i
bx000000000000 h
bx g
bx f
bx e
bx d
bx c
bx b
bx a
bx `
bx _
bx ^
bx ]
bx \
bx [
bx Z
bx Y
bx X
bx W
bx V
bx U
bx T
bx S
xR
xQ
bx P
bx O
bx N
bx M
xL
xK
bx J
xI
b0 H
bx G
bx F
b0 E
bx D
xC
bx B
xA
x@
x?
bx >
bx =
bx <
x;
bx :
bx 9
bx 8
bx 7
bx 6
bx 5
x4
b0 3
bx0 2
bx 1
bx 0
bx /
bx .
bx -
1,
0+
bx *
bx )
b0 (
x'
bx &
x%
bx $
bx #
1"
0!
$end
#5000
b1 x
b101 6
b101 q
b1 y
b101 *
b101 -
b101 u
b101 M
b101 Y
b100 2
04
b101 W
b101 O
b101 V
b0 U
b0 P
b0 T
b100000000000 l
b101 E
b101 m
b100000000100 j
1K
b0 Z
b0 9
b0 ^
b0 s
b0 [
b0 &
b0 /
b0 w
b0 7
b0 ]
b0 r
1;
b0 5
b0 e
0%
0?
0'
0@
0A
0C
0I
1L
0Q
0R
b0 N
b0 X
b0 c
b0 D
b0 d
b0 f
b101 k
b1 i
b10100000000000000000000 h
b1 <
b1 n
b0 )
b0 .
b0 v
b0 G
b0 \
b0 :
b0 o
b101 8
b101 p
b10011 `
b0 b
b0 a
b100 =
b10100000000000010010011 1
b10100000000000010010011 _
b10100000000000010010011 g
b10100000000000010010011 #
b10100000000000010010011 F
b10100000000000010010011 ~
b0 !"
b100 >
b101 J
b101 B
b0 $
b0 0
b0 }
b0 S
b100000 t
1!
1+
#10000
0!
0+
#15000
b100000 t
1!
1+
#20000
0!
0+
#25000
0,
b100000 t
1!
1+
#30000
0!
0+
#35000
b111 6
b111 q
b11 y
b111 *
b111 -
b111 u
b111 M
b111 Y
b110 2
b111 W
b111 O
b111 V
b10 l
b111 E
b111 m
b100000000110 j
b111 k
b10 i
b11100000000000000000000 h
b10 <
b10 n
b111 8
b111 p
b1000 =
b11100000000000100010011 1
b11100000000000100010011 _
b11100000000000100010011 g
b11100000000000100010011 #
b11100000000000100010011 F
b11100000000000100010011 ~
b1 !"
b1000 >
b1011 J
b1011 B
b100 $
b100 0
b100 }
b100 S
1!
1+
#40000
0!
0+
#45000
b11 x
b1100 6
b1100 q
b0 y
b101 U
b101 P
b101 T
b1100 *
b1100 -
b1100 u
b1100 M
b1100 Y
0K
b111 [
b111 &
b111 /
b111 w
b111 7
b111 ]
b111 r
b111 W
b111 O
b111 V
b100000000010 l
b10 E
b10 m
b1000000000000010 j
b101 Z
b101 9
b101 ^
b101 s
1;
0L
b10 k
b11 i
b1000001000000000000000 h
b11 <
b11 n
b1 :
b1 o
b10 8
b10 p
b110011 `
b1100 =
b1000001000000110110011 1
b1000001000000110110011 _
b1000001000000110110011 g
b1000001000000110110011 #
b1000001000000110110011 F
b1000001000000110110011 ~
b10 !"
b1100 >
b1010 J
b1010 B
b1000 $
b1000 0
b1000 }
b1000 S
1!
1+
#50000
0!
0+
#55000
b0 x
b0 6
b0 q
b0 y
b0 U
b0 P
b0 T
b0 *
b0 -
b0 u
b0 M
b0 Y
b0 2
b1100 [
b1100 &
b1100 /
b1100 w
b1100 7
b1100 ]
b1100 r
b0 W
b0 O
b0 V
b0 l
b0 E
b0 m
b10100000000010 j
b0 Z
b0 9
b0 ^
b0 s
1%
1?
1L
b1 D
b1 d
b1 f
0;
b11 k
b0 i
b1100000010000000000000 h
b0 <
b0 n
b10 )
b10 .
b10 v
b10 G
b10 \
b0 :
b0 o
b11 8
b11 p
b100011 `
b10 b
b10000 =
b1100000010000000100011 1
b1100000010000000100011 _
b1100000010000000100011 g
b1100000010000000100011 #
b1100000010000000100011 F
b1100000010000000100011 ~
b11 !"
b10000 >
b1100 J
b1100 B
b1100 $
b1100 0
b1100 }
b1100 S
1!
1+
#60000
0!
0+
#65000
b10100 6
b10100 q
b0 j
1K
b0 [
b0 &
b0 /
b0 w
b0 7
b0 ]
b0 r
1;
b10 5
b10 e
1C
0%
0?
0L
b100 D
b100 d
b100 f
b0 k
b0 h
b0 )
b0 .
b0 v
b0 G
b0 \
b0 8
b0 p
b1101111 `
b0 b
b10000 =
b1101111 1
b1101111 _
b1101111 g
b1101111 #
b1101111 F
b1101111 ~
b100 !"
b10100 >
b10000 J
b10000 B
b10000 $
b10000 0
b10000 }
b10000 S
1!
1+
